algokit_py/__init__.py
algokit_py/search/__init__.py
algokit_py/search/binary.py
algokit_py/search/linear.py
algokit_py/sort/__init__.py
algokit_py/sort/insertion.py
algokit_py-0.2.0.dist-info/METADATA
algokit_py-0.2.0.dist-info/WHEEL
algokit_py-0.2.0.dist-info/top_level.txt
algokit_py-0.2.0.dist-info/RECORD
