Metadata-Version: 2.4
Name: algokit-py
Version: 0.2.0
Summary: A minimal Python algorithms library with clean implementations of search algorithms
Author: Chanaka Prasanna
License: MIT
Classifier: Programming Language :: Python :: 3
Classifier: License :: OSI Approved :: MIT License
Classifier: Operating System :: OS Independent
Requires-Python: >=3.9
